cliente_modelo/__init__.py
cliente_modelo/cliente.py
tumodelodeclientes-0.1.dist-info/METADATA
tumodelodeclientes-0.1.dist-info/WHEEL
tumodelodeclientes-0.1.dist-info/top_level.txt
tumodelodeclientes-0.1.dist-info/RECORD
