Metadata-Version: 2.4
Name: TuModeloDeClientes
Version: 0.1
Summary: Modelo de Clientes para una página de compras
Author: Tu Nombre Apellido
Author-email: tunombre@correo.com
Classifier: Programming Language :: Python :: 3
Classifier: Operating System :: OS Independent
Requires-Python: >=3.6
Dynamic: author
Dynamic: author-email
Dynamic: classifier
Dynamic: requires-python
Dynamic: summary
